hello/__init__.py
hello/hello.py
hello/pdf2text.py
priteshpdf-1.0.dist-info/LICENSE
priteshpdf-1.0.dist-info/METADATA
priteshpdf-1.0.dist-info/WHEEL
priteshpdf-1.0.dist-info/top_level.txt
priteshpdf-1.0.dist-info/RECORD
