Metadata-Version: 2.1
Name: priteshpdf
Version: 1.0
Summary: fgcgfgcgvcfgfgcvg fgcfgfgfgvcg cgf 
Home-page: UNKNOWN
Author: UNKNOWN
Author-email: UNKNOWN
License: UNKNOWN
Platform: UNKNOWN
